llama_index/py.typed
llama_index/vector_stores/faiss/__init__.py
llama_index/vector_stores/faiss/base.py
llama_index/vector_stores/faiss/map_store.py
llama_index_vector_stores_faiss-0.5.0.dist-info/METADATA
llama_index_vector_stores_faiss-0.5.0.dist-info/WHEEL
llama_index_vector_stores_faiss-0.5.0.dist-info/licenses/LICENSE
llama_index_vector_stores_faiss-0.5.0.dist-info/RECORD
