Metadata-Version: 2.4
Name: llama-index-vector-stores-faiss
Version: 0.5.0
Summary: llama-index vector_stores faiss integration
Author-email: Your Name <you@example.com>
License-Expression: MIT
License-File: LICENSE
Requires-Python: <4.0,>=3.9
Requires-Dist: llama-index-core<0.14,>=0.13.0
